{
  "name": "Solicitor General",
  "totalSpendingFormatted": "$3.9B",
  "percentage": 1.890274201247263,
  "percentageFormatted": "1.9%",
  "categories": [
    {
      "name": "Solicitor General → Agencies, Boards and Commissions → Operations",
      "amount": 0.0009347529999999999
    },
    {
      "name": "Solicitor General → Correctional Services → Operations",
      "amount": 1.3174446739999996
    },
    {
      "name": "Solicitor General → Correctional Services → Offender Rehabilitation Programs",
      "amount": 0.003353685
    },
    {
      "name": "Solicitor General → Correctional Services → Community Residential / Non-Residential Client Services",
      "amount": 0.009196529
    },
    {
      "name": "Solicitor General → Correctional Services → Other",
      "amount": 0.00008931999999999999
    },
    {
      "name": "Solicitor General → Data Insights and Strategic Initiatives → Operations",
      "amount": 0.00388241
    },
    {
      "name": "Solicitor General → Emergency Planning and Management → Operations",
      "amount": 0.116240565
    },
    {
      "name": "Solicitor General → Emergency Planning and Management → Grants for Forensic Services",
      "amount": 0.00269
    },
    {
      "name": "Solicitor General → Emergency Planning and Management → Grants for Fire Safety",
      "amount": 0.002557966
    },
    {
      "name": "Solicitor General → Emergency Services Telecommunications → Operations",
      "amount": 0.060524896
    },
    {
      "name": "Solicitor General → Emergency Services Telecommunications → Next Generation 9-1-1",
      "amount": 0.078918755
    },
    {
      "name": "Solicitor General → Health Services → Operations",
      "amount": 0.047971983999999995
    },
    {
      "name": "Solicitor General → Health Services → Other",
      "amount": 0.000651625
    },
    {
      "name": "Solicitor General → Infrastructure → Operations",
      "amount": 0.245144429
    },
    {
      "name": "Solicitor General → Inspectorate → Operations",
      "amount": 0.009516043
    },
    {
      "name": "Solicitor General → Justice Technology Services → Operations",
      "amount": 0.07596900599999999
    },
    {
      "name": "Solicitor General → Ministry Administration → Operations",
      "amount": 0.075859121
    },
    {
      "name": "Solicitor General → Ontario Provincial Police → Operations",
      "amount": 1.6412089760000002
    },
    {
      "name": "Solicitor General → Policy and Strategic Planning Division → Operations",
      "amount": 0.008944373
    },
    {
      "name": "Solicitor General → Public Safety Division → Operations",
      "amount": 0.15694872199999998
    },
    {
      "name": "Solicitor General → Public Safety Division → Community Safety and Policing Grant",
      "amount": 0.089488377
    },
    {
      "name": "Solicitor General → Public Safety Division → Grants for Municipal RIDE Programs",
      "amount": 0.0024
    },
    {
      "name": "Solicitor General → Public Safety Division → Miscellaneous Grants - Policing Services",
      "amount": 0.041052168
    },
    {
      "name": "Solicitor General → Public Safety Division → Federal-Provincial First Nations Policing Agreement",
      "amount": 0.074304226
    },
    {
      "name": "Solicitor General → Public Safety Division → Court Security",
      "amount": 0.125
    },
    {
      "name": "Solicitor General → Public Safety Division → First Nations Officer Fund",
      "amount": 0.006610391
    },
    {
      "name": "Solicitor General → Public Safety Division → Federal-Provincial First Nations Policing Agreements",
      "amount": 0.018477826
    },
    {
      "name": "Solicitor General → Public Safety Division → Policing Equipment",
      "amount": 0.00259734
    },
    {
      "name": "Solicitor General → Public Safety Division → Other",
      "amount": 0.001758911
    },
    {
      "name": "Solicitor General → Unreported",
      "amount": -0.31473707099999926
    }
  ],
  "spending_data": {
    "name": "Solicitor General",
    "amount": 3.905,
    "children": [
      {
        "name": "Solicitor General → Agencies, Boards and Commissions",
        "children": [
          {
            "name": "Solicitor General → Agencies, Boards and Commissions → Operations",
            "amount": 0.0009347529999999999
          }
        ]
      },
      {
        "name": "Solicitor General → Correctional Services",
        "children": [
          {
            "name": "Solicitor General → Correctional Services → Operations",
            "amount": 1.3174446739999996
          },
          {
            "name": "Solicitor General → Correctional Services → Offender Rehabilitation Programs",
            "amount": 0.003353685
          },
          {
            "name": "Solicitor General → Correctional Services → Community Residential / Non-Residential Client Services",
            "amount": 0.009196529
          },
          {
            "name": "Solicitor General → Correctional Services → Other",
            "amount": 0.00008931999999999999
          }
        ]
      },
      {
        "name": "Solicitor General → Data Insights and Strategic Initiatives",
        "children": [
          {
            "name": "Solicitor General → Data Insights and Strategic Initiatives → Operations",
            "amount": 0.00388241
          }
        ]
      },
      {
        "name": "Solicitor General → Emergency Planning and Management",
        "children": [
          {
            "name": "Solicitor General → Emergency Planning and Management → Operations",
            "amount": 0.116240565
          },
          {
            "name": "Solicitor General → Emergency Planning and Management → Grants for Forensic Services",
            "amount": 0.00269
          },
          {
            "name": "Solicitor General → Emergency Planning and Management → Grants for Fire Safety",
            "amount": 0.002557966
          }
        ]
      },
      {
        "name": "Solicitor General → Emergency Services Telecommunications",
        "children": [
          {
            "name": "Solicitor General → Emergency Services Telecommunications → Operations",
            "amount": 0.060524896
          },
          {
            "name": "Solicitor General → Emergency Services Telecommunications → Next Generation 9-1-1",
            "amount": 0.078918755
          }
        ]
      },
      {
        "name": "Solicitor General → Health Services",
        "children": [
          {
            "name": "Solicitor General → Health Services → Operations",
            "amount": 0.047971983999999995
          },
          {
            "name": "Solicitor General → Health Services → Other",
            "amount": 0.000651625
          }
        ]
      },
      {
        "name": "Solicitor General → Infrastructure",
        "children": [
          {
            "name": "Solicitor General → Infrastructure → Operations",
            "amount": 0.245144429
          }
        ]
      },
      {
        "name": "Solicitor General → Inspectorate",
        "children": [
          {
            "name": "Solicitor General → Inspectorate → Operations",
            "amount": 0.009516043
          }
        ]
      },
      {
        "name": "Solicitor General → Justice Technology Services",
        "children": [
          {
            "name": "Solicitor General → Justice Technology Services → Operations",
            "amount": 0.07596900599999999
          }
        ]
      },
      {
        "name": "Solicitor General → Ministry Administration",
        "children": [
          {
            "name": "Solicitor General → Ministry Administration → Operations",
            "amount": 0.075859121
          }
        ]
      },
      {
        "name": "Solicitor General → Ontario Provincial Police",
        "children": [
          {
            "name": "Solicitor General → Ontario Provincial Police → Operations",
            "amount": 1.6412089760000002
          }
        ]
      },
      {
        "name": "Solicitor General → Policy and Strategic Planning Division",
        "children": [
          {
            "name": "Solicitor General → Policy and Strategic Planning Division → Operations",
            "amount": 0.008944373
          }
        ]
      },
      {
        "name": "Solicitor General → Public Safety Division",
        "children": [
          {
            "name": "Solicitor General → Public Safety Division → Operations",
            "amount": 0.15694872199999998
          },
          {
            "name": "Solicitor General → Public Safety Division → Community Safety and Policing Grant",
            "amount": 0.089488377
          },
          {
            "name": "Solicitor General → Public Safety Division → Grants for Municipal RIDE Programs",
            "amount": 0.0024
          },
          {
            "name": "Solicitor General → Public Safety Division → Miscellaneous Grants - Policing Services",
            "amount": 0.041052168
          },
          {
            "name": "Solicitor General → Public Safety Division → Federal-Provincial First Nations Policing Agreement",
            "amount": 0.074304226
          },
          {
            "name": "Solicitor General → Public Safety Division → Court Security",
            "amount": 0.125
          },
          {
            "name": "Solicitor General → Public Safety Division → First Nations Officer Fund",
            "amount": 0.006610391
          },
          {
            "name": "Solicitor General → Public Safety Division → Federal-Provincial First Nations Policing Agreements",
            "amount": 0.018477826
          },
          {
            "name": "Solicitor General → Public Safety Division → Policing Equipment",
            "amount": 0.00259734
          },
          {
            "name": "Solicitor General → Public Safety Division → Other",
            "amount": 0.001758911
          }
        ]
      },
      {
        "name": "Solicitor General → Unreported",
        "amount": -0.31473707099999926
      }
    ]
  },
  "generatedAt": "2025-07-09T21:53:36.589Z"
}